server/__init__.py
server/app.py
server/model_loader.py
server/utils.py
sonosco/__init__.py
sonosco/infer.py
sonosco/modelwrapper.py
sonosco/test.py
sonosco/utils.py
sonosco/blocks/__init__.py
sonosco/blocks/attention.py
sonosco/blocks/modules.py
sonosco/common/__init__.py
sonosco/common/audio_tools.py
sonosco/common/click_extensions.py
sonosco/common/constants.py
sonosco/common/global_settings.py
sonosco/common/noise_makers.py
sonosco/common/path_utils.py
sonosco/common/serialization_utils.py
sonosco/common/utils.py
sonosco/config/__init__.py
sonosco/config/global_settings.py
sonosco/datasets/__init__.py
sonosco/datasets/dataset.py
sonosco/datasets/loader.py
sonosco/datasets/processor.py
sonosco/datasets/samplers.py
sonosco/datasets/download_datasets/__init__.py
sonosco/datasets/download_datasets/an4.py
sonosco/datasets/download_datasets/common_voice.py
sonosco/datasets/download_datasets/create_manifest.py
sonosco/datasets/download_datasets/librispeech.py
sonosco/datasets/download_datasets/merge_manifests.py
sonosco/datasets/download_datasets/ted3.py
sonosco/datasets/download_datasets/voxforge.py
sonosco/decoders/__init__.py
sonosco/decoders/beam_decoder.py
sonosco/decoders/decoder.py
sonosco/decoders/greedy_decoder.py
sonosco/inference/__init__.py
sonosco/inference/asr.py
sonosco/inference/deepspeech2_inference.py
sonosco/inference/dummp_asr.py
sonosco/inference/las_inference.py
sonosco/inputs/__init__.py
sonosco/inputs/audio.py
sonosco/inputs/dummy_input.py
sonosco/model/__init__.py
sonosco/model/deserializer.py
sonosco/model/serialization.py
sonosco/model/serializer.py
sonosco/models/__init__.py
sonosco/models/attention.py
sonosco/models/deepspeech2.py
sonosco/models/deepspeech2_inference.py
sonosco/models/deepspeech2_old.py
sonosco/models/deepspeech2_sonosco.py
sonosco/models/modules.py
sonosco/models/seq2seq_las.py
sonosco/models/seq2seq_tds.py
sonosco/models/seq2seq_tds_experimental.py
sonosco/models/seq2seq_tds_experimental_v2.py
sonosco-1.0.1.dist-info/LICENSE.txt
sonosco-1.0.1.dist-info/METADATA
sonosco-1.0.1.dist-info/WHEEL
sonosco-1.0.1.dist-info/top_level.txt
sonosco-1.0.1.dist-info/RECORD
